asyncio_task_queues/__init__.py
asyncio_task_queues/app.py
asyncio_task_queues/broker.py
asyncio_task_queues/click.py
asyncio_task_queues/event.py
asyncio_task_queues/fastapi.py
asyncio_task_queues/flask.py
asyncio_task_queues/job.py
asyncio_task_queues/middleware.py
asyncio_task_queues/redis.py
asyncio_task_queues/schedule.py
asyncio_task_queues/serializer.py
asyncio_task_queues/signature.py
asyncio_task_queues/task.py
asyncio_task_queues/types.py
asyncio_task_queues/worker.py
asyncio_task_queues-0.0.3.dist-info/METADATA
asyncio_task_queues-0.0.3.dist-info/WHEEL
asyncio_task_queues-0.0.3.dist-info/top_level.txt
asyncio_task_queues-0.0.3.dist-info/RECORD
