Metadata-Version: 2.1
Name: asyncio-task-queues
Version: 0.0.3
Summary: Python asyncio-compatible distributed task queues
Author-email: Ben Fiola <benfiola@gmail.com>
Project-URL: Source, https://github.com/benfiola/asyncio-task-queues.git
Requires-Python: >=3.7
Provides-Extra: dev
Requires-Dist: black ; extra == 'dev'
Requires-Dist: build ; extra == 'dev'
Requires-Dist: click ; extra == 'dev'
Requires-Dist: fastapi ; extra == 'dev'
Requires-Dist: flask ; extra == 'dev'
Requires-Dist: isort ; extra == 'dev'
Requires-Dist: mkdocs ; extra == 'dev'
Requires-Dist: pytest ; extra == 'dev'
Requires-Dist: redis ; extra == 'dev'
Requires-Dist: twine ; extra == 'dev'
Requires-Dist: uvicorn ; extra == 'dev'
